{
    "CITY ": {
        "0000": "Not in identifiable city (or size group)",
        "0001": "Aberdeen, SD",
        "0002": "Aberdeen, WA",
        "0003": "Abilene, TX",
        "0004": "Ada, OK",
        "0005": "Adams, MA",
        "0006": "Adrian, MI",
        "0007": "Abington, PA",
        "0010": "Akron, OH",
        "0030": "Alameda, CA",
        "0050": "Albany, NY",
        "0051": "Albany, GA",
        "0052": "Albert Lea, MN",
        "0070": "Albuquerque, NM",
        "0090": "Alexandria, VA",
        "0091": "Alexandria, LA",
        "0100": "Alhambra, CA",
        "0110": "Allegheny, PA",
        "0120": "Aliquippa, PA",
        "0130": "Allentown, PA",
        "0131": "Alliance, OH",
        "0132": "Alpena, MI",
        "0140": "Alton, IL",
        "0150": "Altoona, PA",
        "0160": "Amarillo, TX",
        "0161": "Ambridge, PA",
        "0162": "Ames, IA",
        "0163": "Amesbury, MA",
        "0170": "Amsterdam, NY",
        "0171": "Anaconda, MT",
        "0190": "Anaheim, CA",
        "0210": "Anchorage, AK",
        "0230": "Anderson, IN",
        "0231": "Anderson, SC",
        "0250": "Andover, MA",
        "0270": "Ann Arbor, MI",
        "0271": "Annapolis, MD",
        "0272": "Anniston, AL",
        "0273": "Ansonia, CT",
        "0275": "Antioch, CA",
        "0280": "Appleton, WI",
        "0281": "Ardmore, OK",
        "0282": "Argenta, AR",
        "0283": "Arkansas, KS",
        "0284": "Arden-Arcade, CA",
        "0290": "Arlington, TX",
        "0310": "Arlington, VA",
        "0311": "Arlington, MA",
        "0312": "Arnold, PA",
        "0313": "Asbury Park, NJ",
        "0330": "Asheville, NC",
        "0331": "Ashland, OH",
        "0340": "Ashland, KY",
        "0341": "Ashland, WI",
        "0342": "Ashtabula, OH",
        "0343": "Astoria, OR",
        "0344": "Atchison, KS",
        "0345": "Athens, GA",
        "0346": "Athol, MA",
        "0347": "Athens-Clarke County, GA",
        "0350": "Atlanta, GA",
        "0370": "Atlantic City, NJ",
        "0371": "Attleboro, MA",
        "0390": "Auburn, NY",
        "0391": "Auburn, ME",
        "0410": "Augusta, GA",
        "0411": "Augusta-Richmond County, GA",
        "0430": "Augusta, ME",
        "0450": "Aurora, CO",
        "0470": "Aurora, IL",
        "0490": "Austin, TX",
        "0491": "Austin, MN",
        "0510": "Bakersfield, CA",
        "0530": "Baltimore, MD",
        "0550": "Bangor, ME",
        "0551": "Barberton, OH",
        "0552": "Barre, VT",
        "0553": "Bartlesville, OK",
        "0554": "Batavia, NY",
        "0570": "Bath, ME",
        "0590": "Baton Rouge, LA",
        "0610": "Battle Creek, MI",
        "0630": "Bay City, MI",
        "0640": "Bayamon, PR",
        "0650": "Bayonne, NJ",
        "0651": "Beacon, NY",
        "0652": "Beatrice, NE",
        "0660": "Belleville, IL",
        "0670": "Beaumont, TX",
        "0671": "Beaver Falls, PA",
        "0672": "Bedford, IN",
        "0673": "Bellaire, OH",
        "0680": "Bellevue, WA",
        "0690": "Bellingham, WA",
        "0695": "Belvedere, CA",
        "0700": "Belleville, NJ",
        "0701": "Bellevue, PA",
        "0702": "Belmont, OH",
        "0703": "Belmont, MA",
        "0704": "Beloit, WI",
        "0705": "Bennington, VT",
        "0706": "Benton Harbor, MI",
        "0710": "Berkeley, CA",
        "0711": "Berlin, NH",
        "0712": "Berwick, PA",
        "0720": "Berwyn, IL",
        "0721": "Bessemer, AL",
        "0730": "Bethlehem, PA",
        "0740": "Biddeford, ME",
        "0741": "Big Spring, TX",
        "0742": "Billings, MT",
        "0743": "Biloxi, MS",
        "0750": "Binghamton, NY",
        "0760": "Beverly, MA",
        "0761": "Beverly Hills, CA",
        "0770": "Birmingham, AL",
        "0771": "Birmingham, CT",
        "0772": "Bismarck, ND",
        "0780": "Bloomfield, NJ",
        "0790": "Bloomington, IL",
        "0791": "Bloomington, IN",
        "0792": "Blue Island, IL",
        "0793": "Bluefield, WV",
        "0794": "Blytheville, AR",
        "0795": "Bogalusa, LA",
        "0800": "Boise, ID",
        "0801": "Boone, IA",
        "0810": "Boston, MA",
        "0811": "Boulder, CO",
        "0812": "Bowling Green, KY",
        "0813": "Braddock, PA",
        "0814": "Braden, WA",
        "0815": "Bradford, PA",
        "0816": "Brainerd, MN",
        "0817": "Braintree, MA",
        "0818": "Brawley, CA",
        "0819": "Bremerton, WA",
        "0830": "Bridgeport, CT",
        "0831": "Bridgeton, NJ",
        "0832": "Bristol, CT",
        "0833": "Bristol, PA",
        "0834": "Bristol, VA",
        "0835": "Bristol, TN",
        "0837": "Bristol, RI",
        "0850": "Brockton, MA",
        "0851": "Brookfield, IL",
        "0870": "Brookline, MA"
    }
}